compose/__init__.py
compose_go-2.40.1.dist-info/METADATA
compose_go-2.40.1.dist-info/WHEEL
compose_go-2.40.1.dist-info/entry_points.txt
compose_go-2.40.1.dist-info/licenses/LICENSE
compose_go-2.40.1.dist-info/RECORD
