Metadata-Version: 2.4
Name: compose-go
Version: 2.40.1
Summary: Docker Compose v2 (GoLang) wrapped in a Python Package
License-File: LICENSE
Author: Luã Bida Vacaro
Author-email: luabidaa@gmail.com
Requires-Python: >=3.9,<4
Classifier: Programming Language :: Python :: 3
Classifier: Programming Language :: Python :: 3.9
Classifier: Programming Language :: Python :: 3.10
Classifier: Programming Language :: Python :: 3.11
Classifier: Programming Language :: Python :: 3.12
Classifier: Programming Language :: Python :: 3.13
Classifier: Programming Language :: Python :: 3.14
